README.md
setup.cfg
setup.py
outliers_aarshi/__init__.py
outliers_aarshi/outlier_cmd.py
outliers_aarshi.egg-info/PKG-INFO
outliers_aarshi.egg-info/SOURCES.txt
outliers_aarshi.egg-info/dependency_links.txt
outliers_aarshi.egg-info/top_level.txt