Metadata-Version: 2.1
Name: outliers-aarshi
Version: 0.0.1
Summary: A small package that removes outliers from a pandas dataframe
Home-page: UNKNOWN
Author: Aarshi Arora
Author-email: aarshiarora50@gmail.com
License: UNKNOWN
Platform: UNKNOWN
Classifier: Programming Language :: Python :: 3
Classifier: License :: OSI Approved :: MIT License
Classifier: Operating System :: OS Independent
Requires-Python: >=3.8
